{
    "image": "characters/bf_mouse",
    "iconImage": "bf-mouse",
	"flipX": true,
    "iconColor": "#AF66CE",
    "position": [0, 350],
    "camPosition": [0, 0],
    "anims": [
        {
            "prefix": "idle",
            "postfix": "BF idle dance",
            "looped": true,
            "offset": [-5, 0]
        },
        {
            "prefix": "singLEFT",
            "postfix": "BF NOTE LEFT0",
            "looped": true,
            "offset": [-9, 1]
        },
        {
            "prefix": "singDOWN",
            "postfix": "BF NOTE DOWN0",
            "looped": true,
            "offset": [-29, -39]
        },
        {
            "prefix": "singUP",
            "postfix": "BF NOTE UP0",
            "looped": true,
            "offset": [-64, 67]
        },
        {
            "prefix": "singRIGHT",
            "postfix": "BF NOTE RIGHT0",
            "looped": true,
            "offset": [-54, 7]
        },
        {
            "prefix": "singLEFTmiss",
            "postfix": "BF NOTE LEFT MISS",
            "looped": true,
            "offset": [-9, 1]
        },
        {
            "prefix": "singDOWNmiss",
            "postfix": "BF NOTE DOWN MISS",
            "looped": true,
            "offset": [-29, -39]
        },
        {
            "prefix": "singUPmiss",
            "postfix": "BF NOTE UP MISS",
            "looped": true,
            "offset": [-64, 67]
        },
        {
            "prefix": "singRIGHTmiss",
            "postfix": "BF NOTE RIGHT MISS",
            "looped": true,
            "offset": [-54, 7]
        }
    ]
}